{"init":[{"Yasir Demircan":{"name":"Yasir Demircan","okulno":1168,"notlar":{"math":60,"eng":100,"bio":30}}},{"Erinç Demir":{"name":"Erinç Demir","okulno":2447,"notlar":{"math":20,"eng":50}}},{"Nuri Oruç":{"name":"Nuri Oruç","okulno":4962,"notlar":{"math":70,"eng":20}}},{"Student 1":{"name":"Student 1","okulno":1245,"notlar":{"math":20,"eng":20}}},{"Student 2":{"name":"Student 2","okulno":1452,"notlar":{"math":30,"eng":50}}},{"Student 3":{"name":"Student 3","okulno":7854,"notlar":{"math":70,"eng":70}}},{"Student 4":{"name":"Student 4","okulno":1304,"notlar":{"math":20,"eng":100}}}]}